Metadata-Version: 2.1
Name: paladin-module
Version: 0.2
Summary: Just module for practice. Check out my git hub
Home-page: https://github.com/paladinxb
Author: Ilya Kharkovec
Author-email: paladinxb@gmail.com
